cbor2/__init__.py
cbor2/_decoder.py
cbor2/_encoder.py
cbor2/_types.py
cbor2/decoder.py
cbor2/encoder.py
cbor2/py.typed
cbor2/tool.py
cbor2/types.py
cbor2-5.7.1.dist-info/licenses/LICENSE.txt
cbor2-5.7.1.dist-info/METADATA
cbor2-5.7.1.dist-info/WHEEL
cbor2-5.7.1.dist-info/entry_points.txt
cbor2-5.7.1.dist-info/top_level.txt
cbor2-5.7.1.dist-info/RECORD
