Metadata-Version: 2.4
Name: cbor2
Version: 5.7.1
Summary: CBOR (de)serializer with extensive tag support
Author-email: Alex Grönholm <alex.gronholm@nextday.fi>
License-Expression: MIT
Project-URL: Changelog, https://cbor2.readthedocs.io/en/latest/versionhistory.html
Project-URL: Documentation, https://cbor2.readthedocs.org/en/latest/
Project-URL: Source Code, https://github.com/agronholm/cbor2
Project-URL: Issue Tracker, https://github.com/agronholm/cbor2/issues
Keywords: serialization,cbor
Classifier: Development Status :: 5 - Production/Stable
Classifier: Intended Audience :: Developers
Classifier: Typing :: Typed
Classifier: Programming Language :: Python
Classifier: Programming Language :: Python :: 3
Classifier: Programming Language :: Python :: 3.9
Classifier: Programming Language :: Python :: 3.10
Classifier: Programming Language :: Python :: 3.11
Classifier: Programming Language :: Python :: 3.12
Classifier: Programming Language :: Python :: 3.13
Classifier: Programming Language :: Python :: 3.14
Requires-Python: >=3.9
License-File: LICENSE.txt
Dynamic: license-file
